odoo/addons/helpdesk_portal_restriction/README.rst
odoo/addons/helpdesk_portal_restriction/__init__.py
odoo/addons/helpdesk_portal_restriction/__manifest__.py
odoo/addons/helpdesk_portal_restriction/controllers/__init__.py
odoo/addons/helpdesk_portal_restriction/controllers/main.py
odoo/addons/helpdesk_portal_restriction/i18n/helpdesk_portal_restriction.pot
odoo/addons/helpdesk_portal_restriction/i18n/it.po
odoo/addons/helpdesk_portal_restriction/i18n/pt_BR.po
odoo/addons/helpdesk_portal_restriction/models/__init__.py
odoo/addons/helpdesk_portal_restriction/models/helpdesk_ticket_category.py
odoo/addons/helpdesk_portal_restriction/models/helpdesk_ticket_team.py
odoo/addons/helpdesk_portal_restriction/models/res_partner.py
odoo/addons/helpdesk_portal_restriction/readme/CONTRIBUTORS.md
odoo/addons/helpdesk_portal_restriction/readme/DESCRIPTION.md
odoo/addons/helpdesk_portal_restriction/readme/USAGE.md
odoo/addons/helpdesk_portal_restriction/static/description/icon.png
odoo/addons/helpdesk_portal_restriction/static/description/icon.svg
odoo/addons/helpdesk_portal_restriction/static/description/index.html
odoo/addons/helpdesk_portal_restriction/views/res_partner.xml
odoo_addon_helpdesk_portal_restriction-18.0.1.0.0.4.dist-info/METADATA
odoo_addon_helpdesk_portal_restriction-18.0.1.0.0.4.dist-info/WHEEL
odoo_addon_helpdesk_portal_restriction-18.0.1.0.0.4.dist-info/top_level.txt
odoo_addon_helpdesk_portal_restriction-18.0.1.0.0.4.dist-info/RECORD
